{
  "version": "1.0",
  "updated": "2026-05-12",
  "schema": {
    "status_enum": ["not_contacted", "contacted_no_reply", "followup_1_sent", "followup_2_sent", "paused", "replied", "active", "opted_out"],
    "cadence_days": {"followup_1": 4, "followup_2": 10}
  },
  "contacts": [
    {"email": "ethan@crewai.com", "name": "Ethan", "account": "CrewAI", "title": "Strategy and Revenue Operations", "tier": "P0", "channel": "sam", "first_seen": "2026-05-08", "status": "not_contacted", "intro_sent": null, "followup_1_sent": null, "followup_2_sent": null, "gmail_thread_id": null, "last_message_id": null, "notes": ""},
    {"email": "tim.bourcier@merge.dev", "name": "Tim Bourcier", "account": "Merge", "title": "Revenue Operations, Marketing Lead", "tier": "P1", "channel": "sam", "first_seen": "2026-05-11", "status": "not_contacted", "intro_sent": null, "followup_1_sent": null, "followup_2_sent": null, "gmail_thread_id": null, "last_message_id": null, "notes": ""},
    {"email": "evan.dunn@titanx.io", "name": "Evan Dunn", "account": "TitanX", "title": "Head of Marketing", "tier": "P1", "channel": "sam", "first_seen": "2026-05-10", "status": "opted_out", "intro_sent": null, "followup_1_sent": null, "followup_2_sent": null, "gmail_thread_id": null, "last_message_id": null, "notes": "Opted out 2026-05-12 by Eric"},
    {"email": "elliot@prescientai.com", "name": "Elliot", "account": "PrescientAI", "title": "Head of Growth", "tier": "P1", "channel": "sam", "first_seen": "2026-05-07", "status": "not_contacted", "intro_sent": null, "followup_1_sent": null, "followup_2_sent": null, "gmail_thread_id": null, "last_message_id": null, "notes": ""},
    {"email": "ben@baseoperations.com", "name": "Ben", "account": "BaseOperations", "title": "Chief Marketing Officer", "tier": "P1", "channel": "sam", "first_seen": "2026-05-07", "status": "not_contacted", "intro_sent": null, "followup_1_sent": null, "followup_2_sent": null, "gmail_thread_id": null, "last_message_id": null, "notes": "Reacted 3x in Slack across consecutive days"},
    {"email": "mitch@buildkite.com", "name": "Mitch", "account": "Buildkite", "title": "VP, Brand and Design", "tier": "P1", "channel": "sam", "first_seen": "2026-05-06", "status": "not_contacted", "intro_sent": null, "followup_1_sent": null, "followup_2_sent": null, "gmail_thread_id": null, "last_message_id": null, "notes": "First signup from buildkite.com"},
    {"email": "rory.plunket@sanalabs.com", "name": "Rory Plunket", "account": "Sana Labs", "title": "GTM", "tier": "P2", "channel": "sam", "first_seen": "2026-05-07", "status": "active", "intro_sent": null, "followup_1_sent": null, "followup_2_sent": null, "gmail_thread_id": "19e1c54a62640fdc", "last_message_id": "19e1ce64df10b8e1", "notes": "Active deal led by Sam. Demo held 2026-05-11. Account lists exchanged. Skip automated cadence."},
    {"email": "brendan.chang@tavily.com", "name": "Brendan Chang", "account": "Tavily", "title": "Senior Business Development Representative", "tier": "P2", "channel": "sam", "first_seen": "2026-05-07", "status": "not_contacted", "intro_sent": null, "followup_1_sent": null, "followup_2_sent": null, "gmail_thread_id": null, "last_message_id": null, "notes": ""},
    {"email": "adam.renna@gomotive.com", "name": "Adam Renna", "account": "Gomotive", "title": "Director of Strategic Accounts", "tier": "P0", "channel": "eric", "first_seen": "2026-05-07", "status": "not_contacted", "intro_sent": null, "followup_1_sent": null, "followup_2_sent": null, "gmail_thread_id": null, "last_message_id": null, "notes": "First P0 in eric-p0-leads-new-logos channel"},
    {"email": "olli.auvinen@solita.fi", "name": "Olli Auvinen", "account": "Solita", "title": "Head of Marketing, Finland", "tier": "P0", "channel": "unassigned", "first_seen": "2026-05-11", "status": "not_contacted", "intro_sent": null, "followup_1_sent": null, "followup_2_sent": null, "gmail_thread_id": null, "last_message_id": null, "notes": ""},
    {"email": "debo@devzero.io", "name": "Debo", "account": "DevZero", "title": "CEO and Co-Founder", "tier": "P0", "channel": "unassigned", "first_seen": "2026-05-08", "status": "not_contacted", "intro_sent": null, "followup_1_sent": null, "followup_2_sent": null, "gmail_thread_id": null, "last_message_id": null, "notes": ""},
    {"email": "riley@payra.com", "name": "Riley Lovingood", "account": "Payra", "title": "Co-Founder", "tier": "P1", "channel": "unassigned", "first_seen": "2026-05-12", "status": "not_contacted", "intro_sent": null, "followup_1_sent": null, "followup_2_sent": null, "gmail_thread_id": null, "last_message_id": null, "notes": "Subscribed to Sumble Pro 2026-05-12"},
    {"email": "thomas@payra.com", "name": "Thomas", "account": "Payra", "title": "Co-Founder", "tier": "P1", "channel": "unassigned", "first_seen": "2026-05-11", "status": "not_contacted", "intro_sent": null, "followup_1_sent": null, "followup_2_sent": null, "gmail_thread_id": null, "last_message_id": null, "notes": ""},
    {"email": "vivek.uniyal@granica.ai", "name": "Vivek Uniyal", "account": "Granica", "title": "Enterprise Sales Director", "tier": "P1", "channel": "unassigned", "first_seen": "2026-05-11", "status": "not_contacted", "intro_sent": null, "followup_1_sent": null, "followup_2_sent": null, "gmail_thread_id": null, "last_message_id": null, "notes": ""},
    {"email": "eric@fytt.io", "name": "Eric", "account": "Fytt", "title": "Chief Executive Officer", "tier": "P1", "channel": "unassigned", "first_seen": "2026-05-11", "status": "not_contacted", "intro_sent": null, "followup_1_sent": null, "followup_2_sent": null, "gmail_thread_id": null, "last_message_id": null, "notes": "First signup from fytt.io"},
    {"email": "sean@iorad.com", "name": "Sean", "account": "Iorad", "title": "Chief Revenue Officer", "tier": "P1", "channel": "unassigned", "first_seen": "2026-05-11", "status": "opted_out", "intro_sent": null, "followup_1_sent": null, "followup_2_sent": null, "gmail_thread_id": null, "last_message_id": null, "notes": "Opted out 2026-05-12 by Eric"},
    {"email": "andrea@metarouter.io", "name": "Andrea", "account": "MetaRouter", "title": "Head of Commercial Operations", "tier": "P1", "channel": "unassigned", "first_seen": "2026-05-11", "status": "not_contacted", "intro_sent": null, "followup_1_sent": null, "followup_2_sent": null, "gmail_thread_id": null, "last_message_id": null, "notes": ""},
    {"email": "bjourdan@wiremind.io", "name": "B. Jourdan", "account": "Wiremind", "title": "CRO Wiremind Entertainment - EVENTORI", "tier": "P1", "channel": "unassigned", "first_seen": "2026-05-11", "status": "not_contacted", "intro_sent": null, "followup_1_sent": null, "followup_2_sent": null, "gmail_thread_id": null, "last_message_id": null, "notes": "First signup from wiremind.io"},
    {"email": "sshoham@openobserve.ai", "name": "Shani Shoham", "account": "OpenObserve", "title": "Chief Revenue Officer", "tier": "P1", "channel": "unassigned", "first_seen": "2026-05-08", "status": "not_contacted", "intro_sent": null, "followup_1_sent": null, "followup_2_sent": null, "gmail_thread_id": null, "last_message_id": null, "notes": "CSV export activity"},
    {"email": "john@symetryml.net", "name": "John", "account": "SymetryML", "title": "Chief Commercial Officer", "tier": "P1", "channel": "unassigned", "first_seen": "2026-05-07", "status": "contacted_no_reply", "intro_sent": "2026-05-07", "followup_1_sent": null, "followup_2_sent": null, "gmail_thread_id": "19e036aec7b2505c", "last_message_id": "19e036e9a04fb745", "notes": "Intro sent 2026-05-07 subject 'A play for SymetryML\\'s pharma list'. Follow-up #1 drafted 2026-05-12."},
    {"email": "tenzin@vooma.ai", "name": "Tenzin", "account": "Vooma", "title": "Head of Growth", "tier": "P1", "channel": "unassigned", "first_seen": "2026-05-07", "status": "not_contacted", "intro_sent": null, "followup_1_sent": null, "followup_2_sent": null, "gmail_thread_id": null, "last_message_id": null, "notes": ""},
    {"email": "elliot@befrontier.com", "name": "Elliot O'Connor", "account": "BeFrontier", "title": "Founder and CEO", "tier": "P1", "channel": "unassigned", "first_seen": "2026-05-07", "status": "not_contacted", "intro_sent": null, "followup_1_sent": null, "followup_2_sent": null, "gmail_thread_id": null, "last_message_id": null, "notes": "Subscribed to Sumble Pro 2026-05-07"},
    {"email": "lolita@spotlight.ai", "name": "Lolita", "account": "Spotlight", "title": "VP GTM Ops and Marketing Innovation", "tier": "P1", "channel": "unassigned", "first_seen": "2026-05-07", "status": "not_contacted", "intro_sent": null, "followup_1_sent": null, "followup_2_sent": null, "gmail_thread_id": null, "last_message_id": null, "notes": ""},
    {"email": "lucas@sofiaone.co", "name": "Lucas", "account": "Sofiaone", "title": "Head of Growth", "tier": "P1", "channel": "unassigned", "first_seen": "2026-05-07", "status": "not_contacted", "intro_sent": null, "followup_1_sent": null, "followup_2_sent": null, "gmail_thread_id": null, "last_message_id": null, "notes": "First signup from sofiaone.co"},
    {"email": "simon.ryan@zapbi.com", "name": "Simon Ryan", "account": "ZapBI", "title": "Head of Marketing", "tier": "P1", "channel": "unassigned", "first_seen": "2026-05-07", "status": "not_contacted", "intro_sent": null, "followup_1_sent": null, "followup_2_sent": null, "gmail_thread_id": null, "last_message_id": null, "notes": ""},
    {"email": "graham@ioriver.io", "name": "Graham", "account": "IORiver", "title": "GTM", "tier": "P2", "channel": "unassigned", "first_seen": "2026-05-12", "status": "not_contacted", "intro_sent": null, "followup_1_sent": null, "followup_2_sent": null, "gmail_thread_id": null, "last_message_id": null, "notes": ""},
    {"email": "danny.rogan@sekuro.io", "name": "Danny Rogan", "account": "Sekuro", "title": "Sales Manager - Corporate and Enterprise", "tier": "P2", "channel": "unassigned", "first_seen": "2026-05-07", "status": "not_contacted", "intro_sent": null, "followup_1_sent": null, "followup_2_sent": null, "gmail_thread_id": null, "last_message_id": null, "notes": ""},
    {"email": "tom.nicholson@sekuro.io", "name": "Tom Nicholson", "account": "Sekuro", "title": "Senior Account Director - Strategic Clients", "tier": "P2", "channel": "unassigned", "first_seen": "2026-05-07", "status": "not_contacted", "intro_sent": null, "followup_1_sent": null, "followup_2_sent": null, "gmail_thread_id": null, "last_message_id": null, "notes": ""},
    {"email": "anna@hoop.dev", "name": "Anna", "account": "Hoop", "title": "Business Development Representative", "tier": "P2", "channel": "unassigned", "first_seen": "2026-05-07", "status": "not_contacted", "intro_sent": null, "followup_1_sent": null, "followup_2_sent": null, "gmail_thread_id": null, "last_message_id": null, "notes": ""},
    {"email": "ebauman@specterops.io", "name": "E. Bauman", "account": "SpecterOps", "title": "Account Executive (Oregon and NorCal Enterprise)", "tier": "P2", "channel": "unassigned", "first_seen": "2026-05-07", "status": "replied", "intro_sent": "2026-05-05", "followup_1_sent": null, "followup_2_sent": null, "gmail_thread_id": "19dfa6a540ef8420", "last_message_id": "19e042e4d39fc7c2", "notes": "Active back-and-forth. Latest from Bauman 2026-05-07 with target account list attached. Awaiting Eric's substantive response. Skip automated cadence."},
    {"email": "abohmbach@specterops.io", "name": "A. Bohmbach", "account": "SpecterOps", "title": "Enterprise Account Executive", "tier": "P2", "channel": "unassigned", "first_seen": "2026-05-07", "status": "not_contacted", "intro_sent": null, "followup_1_sent": null, "followup_2_sent": null, "gmail_thread_id": null, "last_message_id": null, "notes": ""}
  ]
}
